date_utils/__init__.py
date_utils/dates_utilities.py
lvalibs_date_utils-0.0.17.dist-info/METADATA
lvalibs_date_utils-0.0.17.dist-info/WHEEL
lvalibs_date_utils-0.0.17.dist-info/top_level.txt
lvalibs_date_utils-0.0.17.dist-info/RECORD
