Metadata-Version: 2.1
Name: lvalibs-date-utils
Version: 0.0.17
Summary: Date Utils
Home-page: https://bitbucket.org/lva/lva-date-utils/src/master/
Author: Carlos Soza C.
Author-email: carlos.soza@lvaindices.com
Requires-Python: >=3.9, <4
Requires-Dist: structlog (>=21.5.0)
Requires-Dist: pandas (>=1.4.2)
